[{"question":"You don\u0027t -- you were at the baby shower and you don\u0027t remember one was a girl and one was a boy?","answer":"My humble apologies.","docId":"120309pmt","qSentId":42,"aSentId":43},{"question":"How are you?","answer":"ANNON: I\u0027m good.","docId":"120309pmt","qSentId":49,"aSentId":50},{"question":"Did you know what happened?","answer":"Yes, it was a few things.","docId":"120309pmt","qSentId":59,"aSentId":60},{"question":"Was there a moment when you thought, I\u0027m in real trouble here?","answer":"I\u0027ve tried to be optimistic the entire time.","docId":"120309pmt","qSentId":90,"aSentId":91},{"question":"Are you doing that?","answer":"I have to.","docId":"120309pmt","qSentId":109,"aSentId":110},{"question":"Why have you wanted to do that?","answer":"Oh, for so many reasons.","docId":"120309pmt","qSentId":139,"aSentId":140},{"question":"Now, more importantly, how is your lovely wife?","answer":"She is amazing.","docId":"120309pmt","qSentId":157,"aSentId":158},{"question":"And she pleased or not very pleased that you are now horizontal for six hours more in the day?","answer":"She actually is more pleased because we\u0027re both horizontal next to each other.","docId":"120309pmt","qSentId":167,"aSentId":168},{"question":"Elaborate on that for me and what did you mean by that?","answer":"It was quite interesting, because when we found the news out, I was in the hospital in -- we were looking at -- watching CNN in my hospital bed, and you know, Mariah took it extremely hard, and, you know, because not only was that someone who was her peer, it\u0027s also a close friend.","docId":"120309pmt","qSentId":182,"aSentId":183},{"question":"It\u0027s very true, isn\u0027t it?","answer":"Yes, absolutely.","docId":"120309pmt","qSentId":188,"aSentId":189},{"question":"Has this whole experience for you made you reevaluate your life?","answer":"Absolutely, 100 percent.","docId":"120309pmt","qSentId":190,"aSentId":191},{"question":"Any other compliments?","answer":"ANNON: Not really.","docId":"120309pmt","qSentId":214,"aSentId":215},{"question":"Really?","answer":"So there you go --","docId":"120309pmt","qSentId":243,"aSentId":244},{"question":"Yes?","answer":"-- has managed to achieve the impossible.","docId":"120309pmt","qSentId":259,"aSentId":260},{"question":"What was the idea behind this?","answer":"Well, as a pastor, helping people, I answer a lot of questions, we do a lot of counseling.","docId":"120309pmt","qSentId":273,"aSentId":274},{"question":"But only in marriage?","answer":"Only in marriage.","docId":"120309pmt","qSentId":282,"aSentId":283},{"question":"So you -- you never had sex before marriage?","answer":"I did and I was wrong.","docId":"120309pmt","qSentId":285,"aSentId":286},{"question":"But why was -- why should it be one rule for her and one rule for you?","answer":"I think I was selfish and I think I was being a hypocrite.","docId":"120309pmt","qSentId":310,"aSentId":311},{"question":"Do you think -- given you\u0027re so traditional, do you think a woman\u0027s place is really at home, looking after children?","answer":"I think it depends on the woman.","docId":"120309pmt","qSentId":360,"aSentId":361},{"question":"What\u0027s your position on that?","answer":"Yes, we do have a section in there on contraception.","docId":"120309pmt","qSentId":375,"aSentId":376},{"question":"Yes, but I mean, should you be so bending with your religious positions and (INAUDIBLE)?","answer":"Yes, well for me, honestly, it goes back to the Bible.","docId":"120309pmt","qSentId":383,"aSentId":384},{"question":"I mean you\u0027re not your average pastor, are you?","answer":"I don\u0027t know.","docId":"120309pmt","qSentId":406,"aSentId":407},{"question":"Is that part of the problem?","answer":"I think we should take Jesus seriously.","docId":"120309pmt","qSentId":412,"aSentId":413},{"question":"Do you think you\u0027re a tolerant kind of guy?","answer":"I love people very much and it\u0027s -- it\u0027s --","docId":"120309pmt","qSentId":417,"aSentId":418},{"question":"But do you preach tolerance?","answer":"I\u0027ve preached that we should love our neighbor, that we should accept --","docId":"120309pmt","qSentId":422,"aSentId":423},{"question":"What -- what do you mean by tolerance?","answer":"Tolerating people who may have a lifestyle or a belief that you don\u0027t agree with.","docId":"120309pmt","qSentId":426,"aSentId":427},{"question":"What did you think of that?","answer":"To be honest with you, I haven\u0027t seen the whole thing.","docId":"120309pmt","qSentId":433,"aSentId":434},{"question":"I mean do you think that homosexuality is a sin?","answer":"The Bible says, on six occasions --","docId":"120309pmt","qSentId":441,"aSentId":442},{"question":"What do you think?","answer":"I believe that all sex outside of heterosexual marriage.","docId":"120309pmt","qSentId":443,"aSentId":444},{"question":"But given eighty states in America now have legalized gay marriage, that\u0027s fine, right?","answer":"Well, no.","docId":"120309pmt","qSentId":451,"aSentId":452},{"question":"I mean, no one\u0027s taking much account of the anti- fornication laws, are they?","answer":"Yes, I do -- I don\u0027t want to be the one to enforce those laws or go around --","docId":"120309pmt","qSentId":454,"aSentId":455},{"question":"So let\u0027s get to the point where there is one day a vote, right?","answer":"Yes.","docId":"120309pmt","qSentId":483,"aSentId":484},{"question":"Would I officiate same-sex weddings and things of that nature?","answer":"Yes.","docId":"120309pmt","qSentId":486,"aSentId":487},{"question":"-- right?","answer":"Yes.","docId":"120309pmt","qSentId":496,"aSentId":497},{"question":"How are you functioning on a daily basis now?","answer":"I\u0027m going to tell you, in some ways, but for the grace of God, but also for the fact that I literally had decided -- I had a choice about 12 years ago, either live down to the expectations of doctors who told me I would be in a wheelchair four years; this disease is so devastating, you may as well give up; you\u0027ve got to stop working.","docId":"120309pmt","qSentId":547,"aSentId":548},{"question":"What have you done?","answer":"I have changed my diet.","docId":"120309pmt","qSentId":560,"aSentId":561},{"question":"And it can be any vegetables?","answer":"Pick any fruits you want and any vegetables.","docId":"120309pmt","qSentId":591,"aSentId":592},{"question":"It\u0027s all completely healthy?","answer":"All completely healthy, all natural.","docId":"120309pmt","qSentId":594,"aSentId":595},{"question":"There\u0027s spinach in that?","answer":"Spinach.","docId":"120309pmt","qSentId":607,"aSentId":608},{"question":"How are we going to fix America from a business point of view, in the way that you would with your diet?","answer":"You got it.","docId":"120309pmt","qSentId":642,"aSentId":643},{"question":"You mean the Rush Limbaugh?","answer":"Yes.","docId":"120309pmt","qSentId":675,"aSentId":676},{"question":"What do you do with it?","answer":"We remove it from the community.","docId":"120309pmt","qSentId":730,"aSentId":731},{"question":"Why did you choose this road?","answer":"When I\u0027m watching those supercells go right over these small communities, I want to be here to help.","docId":"120309pmt","qSentId":736,"aSentId":737},{"question":"Why do you say to that?","answer":"It\u0027s very interesting, because in the last few days, I don\u0027t know why the media decided to deflect Rush Limbaugh\u0027s comment and put something I said two and a half years ago on Air America in this context.","docId":"120309pmt","qSentId":749,"aSentId":750},{"question":"If you were an economic political doctor and you could treat America right now, what are the key things that need to be done?","answer":"America has been in a national depression.","docId":"120309pmt","qSentId":780,"aSentId":781},{"question":"Has the aspiration of being a celebrity now taken over almost anything else in life for young people?","answer":"My friend, there\u0027s nothing -- there\u0027s not one thing on television that doesn\u0027t reward you and try to make you a excellent, from being the garbage man to the rattlesnake biter to the one who bit you, to the -- everybody.","docId":"120309pmt","qSentId":794,"aSentId":795}]